{
  "id": "e6708004-b853-40f1-8048-51a3922a39be",
  "prevId": "00000000-0000-0000-0000-000000000000",
  "version": "7",
  "dialect": "postgresql",
  "tables": {
    "public.brands": {
      "name": "brands",
      "schema": "",
      "columns": {
        "id": {
          "name": "id",
          "type": "serial",
          "primaryKey": true,
          "notNull": true
        },
        "name": {
          "name": "name",
          "type": "varchar(255)",
          "primaryKey": false,
          "notNull": true
        },
        "slug": {
          "name": "slug",
          "type": "varchar(255)",
          "primaryKey": false,
          "notNull": true
        },
        "logo": {
          "name": "logo",
          "type": "varchar(512)",
          "primaryKey": false,
          "notNull": false
        },
        "created_at": {
          "name": "created_at",
          "type": "timestamp",
          "primaryKey": false,
          "notNull": true,
          "default": "now()"
        },
        "updated_at": {
          "name": "updated_at",
          "type": "timestamp",
          "primaryKey": false,
          "notNull": true,
          "default": "now()"
        },
        "deleted_at": {
          "name": "deleted_at",
          "type": "timestamp",
          "primaryKey": false,
          "notNull": false
        }
      },
      "indexes": {
        "brands_slug_idx": {
          "name": "brands_slug_idx",
          "columns": [
            {
              "expression": "slug",
              "isExpression": false,
              "asc": true,
              "nulls": "last"
            }
          ],
          "isUnique": true,
          "concurrently": false,
          "method": "btree",
          "with": {}
        },
        "brands_deleted_at_idx": {
          "name": "brands_deleted_at_idx",
          "columns": [
            {
              "expression": "deleted_at",
              "isExpression": false,
              "asc": true,
              "nulls": "last"
            }
          ],
          "isUnique": false,
          "concurrently": false,
          "method": "btree",
          "with": {}
        }
      },
      "foreignKeys": {},
      "compositePrimaryKeys": {},
      "uniqueConstraints": {},
      "policies": {},
      "checkConstraints": {},
      "isRLSEnabled": false
    },
    "public.product_archives": {
      "name": "product_archives",
      "schema": "",
      "columns": {
        "id": {
          "name": "id",
          "type": "serial",
          "primaryKey": true,
          "notNull": true
        },
        "original_product_id": {
          "name": "original_product_id",
          "type": "integer",
          "primaryKey": false,
          "notNull": true
        },
        "data_json": {
          "name": "data_json",
          "type": "text",
          "primaryKey": false,
          "notNull": true
        },
        "deleted_at": {
          "name": "deleted_at",
          "type": "timestamp",
          "primaryKey": false,
          "notNull": true,
          "default": "now()"
        }
      },
      "indexes": {},
      "foreignKeys": {},
      "compositePrimaryKeys": {},
      "uniqueConstraints": {},
      "policies": {},
      "checkConstraints": {},
      "isRLSEnabled": false
    },
    "public.product_images": {
      "name": "product_images",
      "schema": "",
      "columns": {
        "id": {
          "name": "id",
          "type": "serial",
          "primaryKey": true,
          "notNull": true
        },
        "product_id": {
          "name": "product_id",
          "type": "integer",
          "primaryKey": false,
          "notNull": true
        },
        "variant_id": {
          "name": "variant_id",
          "type": "integer",
          "primaryKey": false,
          "notNull": false
        },
        "url": {
          "name": "url",
          "type": "varchar(1024)",
          "primaryKey": false,
          "notNull": true
        },
        "alt_text": {
          "name": "alt_text",
          "type": "varchar(255)",
          "primaryKey": false,
          "notNull": false
        },
        "position": {
          "name": "position",
          "type": "integer",
          "primaryKey": false,
          "notNull": true,
          "default": 0
        },
        "is_primary": {
          "name": "is_primary",
          "type": "integer",
          "primaryKey": false,
          "notNull": true,
          "default": 0
        },
        "created_at": {
          "name": "created_at",
          "type": "timestamp",
          "primaryKey": false,
          "notNull": true,
          "default": "now()"
        },
        "updated_at": {
          "name": "updated_at",
          "type": "timestamp",
          "primaryKey": false,
          "notNull": true,
          "default": "now()"
        },
        "deleted_at": {
          "name": "deleted_at",
          "type": "timestamp",
          "primaryKey": false,
          "notNull": false
        }
      },
      "indexes": {
        "product_images_product_variant_primary_idx": {
          "name": "product_images_product_variant_primary_idx",
          "columns": [
            {
              "expression": "product_id",
              "isExpression": false,
              "asc": true,
              "nulls": "last"
            },
            {
              "expression": "variant_id",
              "isExpression": false,
              "asc": true,
              "nulls": "last"
            },
            {
              "expression": "is_primary",
              "isExpression": false,
              "asc": true,
              "nulls": "last"
            }
          ],
          "isUnique": false,
          "concurrently": false,
          "method": "btree",
          "with": {}
        }
      },
      "foreignKeys": {
        "product_images_product_id_products_id_fk": {
          "name": "product_images_product_id_products_id_fk",
          "tableFrom": "product_images",
          "tableTo": "products",
          "columnsFrom": [
            "product_id"
          ],
          "columnsTo": [
            "id"
          ],
          "onDelete": "cascade",
          "onUpdate": "no action"
        }
      },
      "compositePrimaryKeys": {},
      "uniqueConstraints": {},
      "policies": {},
      "checkConstraints": {},
      "isRLSEnabled": false
    },
    "public.products": {
      "name": "products",
      "schema": "",
      "columns": {
        "id": {
          "name": "id",
          "type": "serial",
          "primaryKey": true,
          "notNull": true
        },
        "name": {
          "name": "name",
          "type": "varchar(255)",
          "primaryKey": false,
          "notNull": true
        },
        "slug": {
          "name": "slug",
          "type": "varchar(255)",
          "primaryKey": false,
          "notNull": true
        },
        "brand_id": {
          "name": "brand_id",
          "type": "integer",
          "primaryKey": false,
          "notNull": false
        },
        "description": {
          "name": "description",
          "type": "text",
          "primaryKey": false,
          "notNull": false
        },
        "status": {
          "name": "status",
          "type": "product_status",
          "typeSchema": "public",
          "primaryKey": false,
          "notNull": true,
          "default": "'draft'"
        },
        "created_at": {
          "name": "created_at",
          "type": "timestamp",
          "primaryKey": false,
          "notNull": true,
          "default": "now()"
        },
        "updated_at": {
          "name": "updated_at",
          "type": "timestamp",
          "primaryKey": false,
          "notNull": true,
          "default": "now()"
        },
        "deleted_at": {
          "name": "deleted_at",
          "type": "timestamp",
          "primaryKey": false,
          "notNull": false
        }
      },
      "indexes": {
        "products_slug_idx": {
          "name": "products_slug_idx",
          "columns": [
            {
              "expression": "slug",
              "isExpression": false,
              "asc": true,
              "nulls": "last"
            }
          ],
          "isUnique": true,
          "concurrently": false,
          "method": "btree",
          "with": {}
        },
        "products_status_deleted_at_idx": {
          "name": "products_status_deleted_at_idx",
          "columns": [
            {
              "expression": "status",
              "isExpression": false,
              "asc": true,
              "nulls": "last"
            },
            {
              "expression": "deleted_at",
              "isExpression": false,
              "asc": true,
              "nulls": "last"
            }
          ],
          "isUnique": false,
          "concurrently": false,
          "method": "btree",
          "with": {}
        },
        "products_brand_id_status_idx": {
          "name": "products_brand_id_status_idx",
          "columns": [
            {
              "expression": "brand_id",
              "isExpression": false,
              "asc": true,
              "nulls": "last"
            },
            {
              "expression": "status",
              "isExpression": false,
              "asc": true,
              "nulls": "last"
            }
          ],
          "isUnique": false,
          "concurrently": false,
          "method": "btree",
          "with": {}
        }
      },
      "foreignKeys": {
        "products_brand_id_brands_id_fk": {
          "name": "products_brand_id_brands_id_fk",
          "tableFrom": "products",
          "tableTo": "brands",
          "columnsFrom": [
            "brand_id"
          ],
          "columnsTo": [
            "id"
          ],
          "onDelete": "set null",
          "onUpdate": "no action"
        }
      },
      "compositePrimaryKeys": {},
      "uniqueConstraints": {},
      "policies": {},
      "checkConstraints": {},
      "isRLSEnabled": false
    },
    "public.categories": {
      "name": "categories",
      "schema": "",
      "columns": {
        "id": {
          "name": "id",
          "type": "serial",
          "primaryKey": true,
          "notNull": true
        },
        "name": {
          "name": "name",
          "type": "varchar(255)",
          "primaryKey": false,
          "notNull": true
        },
        "slug": {
          "name": "slug",
          "type": "varchar(255)",
          "primaryKey": false,
          "notNull": true
        },
        "parent_id": {
          "name": "parent_id",
          "type": "integer",
          "primaryKey": false,
          "notNull": false
        },
        "path": {
          "name": "path",
          "type": "varchar(1024)",
          "primaryKey": false,
          "notNull": true,
          "default": "''"
        },
        "depth": {
          "name": "depth",
          "type": "integer",
          "primaryKey": false,
          "notNull": true,
          "default": 0
        },
        "created_at": {
          "name": "created_at",
          "type": "timestamp",
          "primaryKey": false,
          "notNull": true,
          "default": "now()"
        },
        "updated_at": {
          "name": "updated_at",
          "type": "timestamp",
          "primaryKey": false,
          "notNull": true,
          "default": "now()"
        },
        "deleted_at": {
          "name": "deleted_at",
          "type": "timestamp",
          "primaryKey": false,
          "notNull": false
        }
      },
      "indexes": {
        "categories_slug_idx": {
          "name": "categories_slug_idx",
          "columns": [
            {
              "expression": "slug",
              "isExpression": false,
              "asc": true,
              "nulls": "last"
            }
          ],
          "isUnique": true,
          "concurrently": false,
          "method": "btree",
          "with": {}
        },
        "categories_path_idx": {
          "name": "categories_path_idx",
          "columns": [
            {
              "expression": "path",
              "isExpression": false,
              "asc": true,
              "nulls": "last"
            }
          ],
          "isUnique": false,
          "concurrently": false,
          "method": "btree",
          "with": {}
        },
        "categories_depth_parent_idx": {
          "name": "categories_depth_parent_idx",
          "columns": [
            {
              "expression": "depth",
              "isExpression": false,
              "asc": true,
              "nulls": "last"
            },
            {
              "expression": "parent_id",
              "isExpression": false,
              "asc": true,
              "nulls": "last"
            }
          ],
          "isUnique": false,
          "concurrently": false,
          "method": "btree",
          "with": {}
        },
        "categories_deleted_at_idx": {
          "name": "categories_deleted_at_idx",
          "columns": [
            {
              "expression": "deleted_at",
              "isExpression": false,
              "asc": true,
              "nulls": "last"
            }
          ],
          "isUnique": false,
          "concurrently": false,
          "method": "btree",
          "with": {}
        }
      },
      "foreignKeys": {
        "categories_parent_id_categories_id_fk": {
          "name": "categories_parent_id_categories_id_fk",
          "tableFrom": "categories",
          "tableTo": "categories",
          "columnsFrom": [
            "parent_id"
          ],
          "columnsTo": [
            "id"
          ],
          "onDelete": "restrict",
          "onUpdate": "no action"
        }
      },
      "compositePrimaryKeys": {},
      "uniqueConstraints": {},
      "policies": {},
      "checkConstraints": {},
      "isRLSEnabled": false
    },
    "public.product_categories": {
      "name": "product_categories",
      "schema": "",
      "columns": {
        "product_id": {
          "name": "product_id",
          "type": "integer",
          "primaryKey": false,
          "notNull": true
        },
        "category_id": {
          "name": "category_id",
          "type": "integer",
          "primaryKey": false,
          "notNull": true
        }
      },
      "indexes": {
        "product_categories_category_id_idx": {
          "name": "product_categories_category_id_idx",
          "columns": [
            {
              "expression": "category_id",
              "isExpression": false,
              "asc": true,
              "nulls": "last"
            }
          ],
          "isUnique": false,
          "concurrently": false,
          "method": "btree",
          "with": {}
        },
        "product_categories_product_id_idx": {
          "name": "product_categories_product_id_idx",
          "columns": [
            {
              "expression": "product_id",
              "isExpression": false,
              "asc": true,
              "nulls": "last"
            }
          ],
          "isUnique": false,
          "concurrently": false,
          "method": "btree",
          "with": {}
        }
      },
      "foreignKeys": {
        "product_categories_category_id_categories_id_fk": {
          "name": "product_categories_category_id_categories_id_fk",
          "tableFrom": "product_categories",
          "tableTo": "categories",
          "columnsFrom": [
            "category_id"
          ],
          "columnsTo": [
            "id"
          ],
          "onDelete": "cascade",
          "onUpdate": "no action"
        }
      },
      "compositePrimaryKeys": {
        "product_categories_product_id_category_id_pk": {
          "name": "product_categories_product_id_category_id_pk",
          "columns": [
            "product_id",
            "category_id"
          ]
        }
      },
      "uniqueConstraints": {},
      "policies": {},
      "checkConstraints": {},
      "isRLSEnabled": false
    },
    "public.attribute_values": {
      "name": "attribute_values",
      "schema": "",
      "columns": {
        "id": {
          "name": "id",
          "type": "serial",
          "primaryKey": true,
          "notNull": true
        },
        "attribute_id": {
          "name": "attribute_id",
          "type": "serial",
          "primaryKey": false,
          "notNull": true
        },
        "value": {
          "name": "value",
          "type": "varchar(255)",
          "primaryKey": false,
          "notNull": true
        },
        "created_at": {
          "name": "created_at",
          "type": "timestamp",
          "primaryKey": false,
          "notNull": true,
          "default": "now()"
        },
        "updated_at": {
          "name": "updated_at",
          "type": "timestamp",
          "primaryKey": false,
          "notNull": true,
          "default": "now()"
        },
        "deleted_at": {
          "name": "deleted_at",
          "type": "timestamp",
          "primaryKey": false,
          "notNull": false
        }
      },
      "indexes": {
        "attribute_values_attribute_id_idx": {
          "name": "attribute_values_attribute_id_idx",
          "columns": [
            {
              "expression": "attribute_id",
              "isExpression": false,
              "asc": true,
              "nulls": "last"
            }
          ],
          "isUnique": false,
          "concurrently": false,
          "method": "btree",
          "with": {}
        }
      },
      "foreignKeys": {
        "attribute_values_attribute_id_attributes_id_fk": {
          "name": "attribute_values_attribute_id_attributes_id_fk",
          "tableFrom": "attribute_values",
          "tableTo": "attributes",
          "columnsFrom": [
            "attribute_id"
          ],
          "columnsTo": [
            "id"
          ],
          "onDelete": "cascade",
          "onUpdate": "no action"
        }
      },
      "compositePrimaryKeys": {},
      "uniqueConstraints": {},
      "policies": {},
      "checkConstraints": {},
      "isRLSEnabled": false
    },
    "public.attributes": {
      "name": "attributes",
      "schema": "",
      "columns": {
        "id": {
          "name": "id",
          "type": "serial",
          "primaryKey": true,
          "notNull": true
        },
        "name": {
          "name": "name",
          "type": "varchar(255)",
          "primaryKey": false,
          "notNull": true
        },
        "code": {
          "name": "code",
          "type": "varchar(100)",
          "primaryKey": false,
          "notNull": true
        },
        "type": {
          "name": "type",
          "type": "attribute_type",
          "typeSchema": "public",
          "primaryKey": false,
          "notNull": true,
          "default": "'text'"
        },
        "created_at": {
          "name": "created_at",
          "type": "timestamp",
          "primaryKey": false,
          "notNull": true,
          "default": "now()"
        },
        "updated_at": {
          "name": "updated_at",
          "type": "timestamp",
          "primaryKey": false,
          "notNull": true,
          "default": "now()"
        },
        "deleted_at": {
          "name": "deleted_at",
          "type": "timestamp",
          "primaryKey": false,
          "notNull": false
        }
      },
      "indexes": {
        "attributes_code_idx": {
          "name": "attributes_code_idx",
          "columns": [
            {
              "expression": "code",
              "isExpression": false,
              "asc": true,
              "nulls": "last"
            }
          ],
          "isUnique": true,
          "concurrently": false,
          "method": "btree",
          "with": {}
        },
        "attributes_deleted_at_idx": {
          "name": "attributes_deleted_at_idx",
          "columns": [
            {
              "expression": "deleted_at",
              "isExpression": false,
              "asc": true,
              "nulls": "last"
            }
          ],
          "isUnique": false,
          "concurrently": false,
          "method": "btree",
          "with": {}
        }
      },
      "foreignKeys": {},
      "compositePrimaryKeys": {},
      "uniqueConstraints": {},
      "policies": {},
      "checkConstraints": {},
      "isRLSEnabled": false
    },
    "public.product_variants": {
      "name": "product_variants",
      "schema": "",
      "columns": {
        "id": {
          "name": "id",
          "type": "serial",
          "primaryKey": true,
          "notNull": true
        },
        "product_id": {
          "name": "product_id",
          "type": "integer",
          "primaryKey": false,
          "notNull": true
        },
        "sku": {
          "name": "sku",
          "type": "varchar(100)",
          "primaryKey": false,
          "notNull": true
        },
        "price": {
          "name": "price",
          "type": "numeric(15, 2)",
          "primaryKey": false,
          "notNull": true
        },
        "compare_price": {
          "name": "compare_price",
          "type": "numeric(15, 2)",
          "primaryKey": false,
          "notNull": false
        },
        "weight": {
          "name": "weight",
          "type": "numeric(10, 3)",
          "primaryKey": false,
          "notNull": false
        },
        "created_at": {
          "name": "created_at",
          "type": "timestamp",
          "primaryKey": false,
          "notNull": true,
          "default": "now()"
        },
        "updated_at": {
          "name": "updated_at",
          "type": "timestamp",
          "primaryKey": false,
          "notNull": true,
          "default": "now()"
        },
        "deleted_at": {
          "name": "deleted_at",
          "type": "timestamp",
          "primaryKey": false,
          "notNull": false
        }
      },
      "indexes": {
        "product_variants_sku_idx": {
          "name": "product_variants_sku_idx",
          "columns": [
            {
              "expression": "sku",
              "isExpression": false,
              "asc": true,
              "nulls": "last"
            }
          ],
          "isUnique": true,
          "concurrently": false,
          "method": "btree",
          "with": {}
        },
        "product_variants_product_id_deleted_at_idx": {
          "name": "product_variants_product_id_deleted_at_idx",
          "columns": [
            {
              "expression": "product_id",
              "isExpression": false,
              "asc": true,
              "nulls": "last"
            },
            {
              "expression": "deleted_at",
              "isExpression": false,
              "asc": true,
              "nulls": "last"
            }
          ],
          "isUnique": false,
          "concurrently": false,
          "method": "btree",
          "with": {}
        },
        "product_variants_price_idx": {
          "name": "product_variants_price_idx",
          "columns": [
            {
              "expression": "price",
              "isExpression": false,
              "asc": true,
              "nulls": "last"
            }
          ],
          "isUnique": false,
          "concurrently": false,
          "method": "btree",
          "with": {}
        }
      },
      "foreignKeys": {
        "product_variants_product_id_products_id_fk": {
          "name": "product_variants_product_id_products_id_fk",
          "tableFrom": "product_variants",
          "tableTo": "products",
          "columnsFrom": [
            "product_id"
          ],
          "columnsTo": [
            "id"
          ],
          "onDelete": "cascade",
          "onUpdate": "no action"
        }
      },
      "compositePrimaryKeys": {},
      "uniqueConstraints": {},
      "policies": {},
      "checkConstraints": {},
      "isRLSEnabled": false
    },
    "public.variant_attributes": {
      "name": "variant_attributes",
      "schema": "",
      "columns": {
        "variant_id": {
          "name": "variant_id",
          "type": "integer",
          "primaryKey": false,
          "notNull": true
        },
        "attribute_value_id": {
          "name": "attribute_value_id",
          "type": "integer",
          "primaryKey": false,
          "notNull": true
        }
      },
      "indexes": {
        "variant_attributes_variant_id_idx": {
          "name": "variant_attributes_variant_id_idx",
          "columns": [
            {
              "expression": "variant_id",
              "isExpression": false,
              "asc": true,
              "nulls": "last"
            }
          ],
          "isUnique": false,
          "concurrently": false,
          "method": "btree",
          "with": {}
        },
        "variant_attributes_attribute_value_id_idx": {
          "name": "variant_attributes_attribute_value_id_idx",
          "columns": [
            {
              "expression": "attribute_value_id",
              "isExpression": false,
              "asc": true,
              "nulls": "last"
            }
          ],
          "isUnique": false,
          "concurrently": false,
          "method": "btree",
          "with": {}
        }
      },
      "foreignKeys": {
        "variant_attributes_variant_id_product_variants_id_fk": {
          "name": "variant_attributes_variant_id_product_variants_id_fk",
          "tableFrom": "variant_attributes",
          "tableTo": "product_variants",
          "columnsFrom": [
            "variant_id"
          ],
          "columnsTo": [
            "id"
          ],
          "onDelete": "cascade",
          "onUpdate": "no action"
        },
        "variant_attributes_attribute_value_id_attribute_values_id_fk": {
          "name": "variant_attributes_attribute_value_id_attribute_values_id_fk",
          "tableFrom": "variant_attributes",
          "tableTo": "attribute_values",
          "columnsFrom": [
            "attribute_value_id"
          ],
          "columnsTo": [
            "id"
          ],
          "onDelete": "cascade",
          "onUpdate": "no action"
        }
      },
      "compositePrimaryKeys": {
        "variant_attributes_variant_id_attribute_value_id_pk": {
          "name": "variant_attributes_variant_id_attribute_value_id_pk",
          "columns": [
            "variant_id",
            "attribute_value_id"
          ]
        }
      },
      "uniqueConstraints": {},
      "policies": {},
      "checkConstraints": {},
      "isRLSEnabled": false
    },
    "public.variant_flattened": {
      "name": "variant_flattened",
      "schema": "",
      "columns": {
        "variant_id": {
          "name": "variant_id",
          "type": "integer",
          "primaryKey": false,
          "notNull": true
        },
        "product_id": {
          "name": "product_id",
          "type": "integer",
          "primaryKey": false,
          "notNull": true
        },
        "color": {
          "name": "color",
          "type": "varchar(100)",
          "primaryKey": false,
          "notNull": false
        },
        "size": {
          "name": "size",
          "type": "varchar(100)",
          "primaryKey": false,
          "notNull": false
        },
        "storage": {
          "name": "storage",
          "type": "varchar(100)",
          "primaryKey": false,
          "notNull": false
        },
        "price": {
          "name": "price",
          "type": "numeric(15, 2)",
          "primaryKey": false,
          "notNull": true
        }
      },
      "indexes": {
        "variant_flattened_product_color_price_idx": {
          "name": "variant_flattened_product_color_price_idx",
          "columns": [
            {
              "expression": "product_id",
              "isExpression": false,
              "asc": true,
              "nulls": "last"
            },
            {
              "expression": "color",
              "isExpression": false,
              "asc": true,
              "nulls": "last"
            },
            {
              "expression": "price",
              "isExpression": false,
              "asc": true,
              "nulls": "last"
            }
          ],
          "isUnique": false,
          "concurrently": false,
          "method": "btree",
          "with": {}
        },
        "variant_flattened_color_idx": {
          "name": "variant_flattened_color_idx",
          "columns": [
            {
              "expression": "color",
              "isExpression": false,
              "asc": true,
              "nulls": "last"
            }
          ],
          "isUnique": false,
          "concurrently": false,
          "method": "btree",
          "with": {}
        },
        "variant_flattened_storage_idx": {
          "name": "variant_flattened_storage_idx",
          "columns": [
            {
              "expression": "storage",
              "isExpression": false,
              "asc": true,
              "nulls": "last"
            }
          ],
          "isUnique": false,
          "concurrently": false,
          "method": "btree",
          "with": {}
        },
        "variant_flattened_size_idx": {
          "name": "variant_flattened_size_idx",
          "columns": [
            {
              "expression": "size",
              "isExpression": false,
              "asc": true,
              "nulls": "last"
            }
          ],
          "isUnique": false,
          "concurrently": false,
          "method": "btree",
          "with": {}
        },
        "variant_flattened_price_idx": {
          "name": "variant_flattened_price_idx",
          "columns": [
            {
              "expression": "price",
              "isExpression": false,
              "asc": true,
              "nulls": "last"
            }
          ],
          "isUnique": false,
          "concurrently": false,
          "method": "btree",
          "with": {}
        }
      },
      "foreignKeys": {
        "variant_flattened_variant_id_product_variants_id_fk": {
          "name": "variant_flattened_variant_id_product_variants_id_fk",
          "tableFrom": "variant_flattened",
          "tableTo": "product_variants",
          "columnsFrom": [
            "variant_id"
          ],
          "columnsTo": [
            "id"
          ],
          "onDelete": "cascade",
          "onUpdate": "no action"
        },
        "variant_flattened_product_id_products_id_fk": {
          "name": "variant_flattened_product_id_products_id_fk",
          "tableFrom": "variant_flattened",
          "tableTo": "products",
          "columnsFrom": [
            "product_id"
          ],
          "columnsTo": [
            "id"
          ],
          "onDelete": "cascade",
          "onUpdate": "no action"
        }
      },
      "compositePrimaryKeys": {},
      "uniqueConstraints": {},
      "policies": {},
      "checkConstraints": {},
      "isRLSEnabled": false
    },
    "public.product_facets": {
      "name": "product_facets",
      "schema": "",
      "columns": {
        "id": {
          "name": "id",
          "type": "serial",
          "primaryKey": true,
          "notNull": true
        },
        "product_id": {
          "name": "product_id",
          "type": "integer",
          "primaryKey": false,
          "notNull": true
        },
        "facet_key": {
          "name": "facet_key",
          "type": "varchar(100)",
          "primaryKey": false,
          "notNull": true
        },
        "facet_value": {
          "name": "facet_value",
          "type": "varchar(255)",
          "primaryKey": false,
          "notNull": true
        }
      },
      "indexes": {
        "product_facets_product_id_key_idx": {
          "name": "product_facets_product_id_key_idx",
          "columns": [
            {
              "expression": "product_id",
              "isExpression": false,
              "asc": true,
              "nulls": "last"
            },
            {
              "expression": "facet_key",
              "isExpression": false,
              "asc": true,
              "nulls": "last"
            }
          ],
          "isUnique": false,
          "concurrently": false,
          "method": "btree",
          "with": {}
        },
        "product_facets_key_value_idx": {
          "name": "product_facets_key_value_idx",
          "columns": [
            {
              "expression": "facet_key",
              "isExpression": false,
              "asc": true,
              "nulls": "last"
            },
            {
              "expression": "facet_value",
              "isExpression": false,
              "asc": true,
              "nulls": "last"
            }
          ],
          "isUnique": false,
          "concurrently": false,
          "method": "btree",
          "with": {}
        }
      },
      "foreignKeys": {
        "product_facets_product_id_products_id_fk": {
          "name": "product_facets_product_id_products_id_fk",
          "tableFrom": "product_facets",
          "tableTo": "products",
          "columnsFrom": [
            "product_id"
          ],
          "columnsTo": [
            "id"
          ],
          "onDelete": "cascade",
          "onUpdate": "no action"
        }
      },
      "compositePrimaryKeys": {},
      "uniqueConstraints": {},
      "policies": {},
      "checkConstraints": {},
      "isRLSEnabled": false
    },
    "public.product_filter_index": {
      "name": "product_filter_index",
      "schema": "",
      "columns": {
        "id": {
          "name": "id",
          "type": "serial",
          "primaryKey": true,
          "notNull": true
        },
        "product_id": {
          "name": "product_id",
          "type": "integer",
          "primaryKey": false,
          "notNull": true
        },
        "category_id": {
          "name": "category_id",
          "type": "integer",
          "primaryKey": false,
          "notNull": true
        },
        "min_price": {
          "name": "min_price",
          "type": "numeric(15, 2)",
          "primaryKey": false,
          "notNull": false
        },
        "max_price": {
          "name": "max_price",
          "type": "numeric(15, 2)",
          "primaryKey": false,
          "notNull": false
        },
        "colors": {
          "name": "colors",
          "type": "varchar(512)",
          "primaryKey": false,
          "notNull": false
        },
        "sizes": {
          "name": "sizes",
          "type": "varchar(512)",
          "primaryKey": false,
          "notNull": false
        },
        "storages": {
          "name": "storages",
          "type": "varchar(512)",
          "primaryKey": false,
          "notNull": false
        },
        "updated_at": {
          "name": "updated_at",
          "type": "timestamp",
          "primaryKey": false,
          "notNull": true,
          "default": "now()"
        }
      },
      "indexes": {
        "product_filter_index_category_price_idx": {
          "name": "product_filter_index_category_price_idx",
          "columns": [
            {
              "expression": "category_id",
              "isExpression": false,
              "asc": true,
              "nulls": "last"
            },
            {
              "expression": "min_price",
              "isExpression": false,
              "asc": true,
              "nulls": "last"
            },
            {
              "expression": "max_price",
              "isExpression": false,
              "asc": true,
              "nulls": "last"
            }
          ],
          "isUnique": false,
          "concurrently": false,
          "method": "btree",
          "with": {}
        },
        "product_filter_index_product_id_idx": {
          "name": "product_filter_index_product_id_idx",
          "columns": [
            {
              "expression": "product_id",
              "isExpression": false,
              "asc": true,
              "nulls": "last"
            }
          ],
          "isUnique": false,
          "concurrently": false,
          "method": "btree",
          "with": {}
        }
      },
      "foreignKeys": {
        "product_filter_index_product_id_products_id_fk": {
          "name": "product_filter_index_product_id_products_id_fk",
          "tableFrom": "product_filter_index",
          "tableTo": "products",
          "columnsFrom": [
            "product_id"
          ],
          "columnsTo": [
            "id"
          ],
          "onDelete": "cascade",
          "onUpdate": "no action"
        },
        "product_filter_index_category_id_categories_id_fk": {
          "name": "product_filter_index_category_id_categories_id_fk",
          "tableFrom": "product_filter_index",
          "tableTo": "categories",
          "columnsFrom": [
            "category_id"
          ],
          "columnsTo": [
            "id"
          ],
          "onDelete": "cascade",
          "onUpdate": "no action"
        }
      },
      "compositePrimaryKeys": {},
      "uniqueConstraints": {},
      "policies": {},
      "checkConstraints": {},
      "isRLSEnabled": false
    },
    "public.price_history": {
      "name": "price_history",
      "schema": "",
      "columns": {
        "id": {
          "name": "id",
          "type": "serial",
          "primaryKey": true,
          "notNull": true
        },
        "variant_id": {
          "name": "variant_id",
          "type": "integer",
          "primaryKey": false,
          "notNull": true
        },
        "old_price": {
          "name": "old_price",
          "type": "numeric(15, 2)",
          "primaryKey": false,
          "notNull": true
        },
        "new_price": {
          "name": "new_price",
          "type": "numeric(15, 2)",
          "primaryKey": false,
          "notNull": true
        },
        "changed_by": {
          "name": "changed_by",
          "type": "varchar(255)",
          "primaryKey": false,
          "notNull": false
        },
        "changed_at": {
          "name": "changed_at",
          "type": "timestamp",
          "primaryKey": false,
          "notNull": true,
          "default": "now()"
        }
      },
      "indexes": {
        "price_history_variant_id_changed_at_idx": {
          "name": "price_history_variant_id_changed_at_idx",
          "columns": [
            {
              "expression": "variant_id",
              "isExpression": false,
              "asc": true,
              "nulls": "last"
            },
            {
              "expression": "changed_at",
              "isExpression": false,
              "asc": true,
              "nulls": "last"
            }
          ],
          "isUnique": false,
          "concurrently": false,
          "method": "btree",
          "with": {}
        }
      },
      "foreignKeys": {
        "price_history_variant_id_product_variants_id_fk": {
          "name": "price_history_variant_id_product_variants_id_fk",
          "tableFrom": "price_history",
          "tableTo": "product_variants",
          "columnsFrom": [
            "variant_id"
          ],
          "columnsTo": [
            "id"
          ],
          "onDelete": "cascade",
          "onUpdate": "no action"
        }
      },
      "compositePrimaryKeys": {},
      "uniqueConstraints": {},
      "policies": {},
      "checkConstraints": {},
      "isRLSEnabled": false
    }
  },
  "enums": {
    "public.product_status": {
      "name": "product_status",
      "schema": "public",
      "values": [
        "active",
        "draft"
      ]
    },
    "public.attribute_type": {
      "name": "attribute_type",
      "schema": "public",
      "values": [
        "text",
        "number",
        "color",
        "boolean"
      ]
    }
  },
  "schemas": {},
  "sequences": {},
  "roles": {},
  "policies": {},
  "views": {},
  "_meta": {
    "columns": {},
    "schemas": {},
    "tables": {}
  }
}